torusengine/__init__.py
torusengine/camera.py
torusengine/light.py
torusengine/move.py
torusengine/plane.py
torusengine/scene.py
torusengine/status.py
torusengine/utils.py
torusengine/objects/__init__.py
torusengine/objects/sphere.py
torusengine/objects/torus.py
torus_engine-1.5.0.dist-info/LICENSE
torus_engine-1.5.0.dist-info/METADATA
torus_engine-1.5.0.dist-info/WHEEL
torus_engine-1.5.0.dist-info/top_level.txt
torus_engine-1.5.0.dist-info/RECORD
