Metadata-Version: 2.1
Name: torus-engine
Version: 1.5.0
Summary: 3D ASCII character rendering engine
Home-page: https://github.com/lucaalbinati/torus-engine
Author: Luca Albinati
Author-email: luca.albinati@gmail.com
License: UNKNOWN
Project-URL: Bug Tracker, https://github.com/lucaalbinati/torus-engine/issues
Platform: UNKNOWN
Classifier: Programming Language :: Python :: 3
Classifier: License :: OSI Approved :: MIT License
Classifier: Operating System :: OS Independent
Requires-Python: >=3.7
License-File: LICENSE
